{
  "version": "0.1.0",
  "protocol": "x402",
  "name": "Clicks Protocol",
  "description": "Autonomous yield for AI agents",
  "provider": {
    "name": "Clicks Protocol",
    "url": "https://clicksprotocol.xyz",
    "contact": "hello@clicksprotocol.xyz"
  },
  "payment": {
    "methods": [
      {
        "type": "crypto",
        "chain": "base",
        "currency": "USDC",
        "address": "0x23bb0Ea69b2BD2e527D5DbA6093155A6E1D0C0a3"
      }
    ],
    "features": {
      "auto_split": true,
      "yield_earning": true,
      "instant_settlement": true,
      "zero_lockup": true
    }
  },
  "capabilities": {
    "split": {
      "liquid": 0.8,
      "earning": 0.2
    },
    "yield": {
      "enabled": true,
      "provider": "morpho",
      "apy_range": [0.04, 0.08],
      "compound_frequency": "daily"
    }
  },
  "integration": {
    "sdk": {
      "npm": "@clicks-protocol/sdk",
      "repo": "https://github.com/clicks-protocol/clicks-protocol"
    },
    "mcp": {
      "npm": "@clicks-protocol/mcp-server",
      "repo": "https://github.com/clicks-protocol/clicks-protocol"
    }
  },
  "links": {
    "documentation": "https://clicksprotocol.xyz/docs",
    "github": "https://github.com/clicks-protocol",
    "discord": "https://discord.gg/clicks-protocol",
    "twitter": "https://x.com/ClicksProtocol"
  }
}
